MANIFEST.in
README.rst
flake8_thoughtful.py
pyproject.toml
requirements.txt
setup.cfg
setup.py
flake8_thoughtful.egg-info/PKG-INFO
flake8_thoughtful.egg-info/SOURCES.txt
flake8_thoughtful.egg-info/dependency_links.txt
flake8_thoughtful.egg-info/entry_points.txt
flake8_thoughtful.egg-info/not-zip-safe
flake8_thoughtful.egg-info/requires.txt
flake8_thoughtful.egg-info/top_level.txt
libraries/__init__.py
libraries/base_warning.py
libraries/t_bug_catcher/__init__.py
libraries/t_bug_catcher/configure_call_visitor.py
libraries/t_bug_catcher/incorrect_try_block_visitor.py
tests/__init__.py
tests/hook_test.py