Metadata-Version: 2.1
Name: flake8_thoughtful
Version: 0.1.0
Summary: Pre Commit hook for all Thoughtful checks.
Home-page: https://www.thoughtful.ai/
Author: Thoughtful
Author-email: support@thoughtful.ai
Keywords: flake8_thoughtful
Classifier: Intended Audience :: Developers
Classifier: Natural Language :: English
Classifier: Programming Language :: Python :: 3
Classifier: Programming Language :: Python :: 3.9
Requires-Python: >=3.9
Requires-Dist: flake8>=3
